{
  "$type": "QuestBooks.QuestLog.DefaultQuestBooks.BasicQuestBook, QuestBooks",
  "NameKey": "Mods.QuestBooks.VanillaQuests.TestBook6.DisplayName",
  "QuestLines": {
    "$type": "System.Collections.Generic.List`1[[QuestBooks.QuestLog.DefaultQuestLines.BasicQuestLine, QuestBooks]], System.Private.CoreLib",
    "$values": [
      {
        "$type": "QuestBooks.QuestLog.DefaultQuestLines.BasicQuestLine, QuestBooks",
        "ChapterElements": {
          "$type": "System.Collections.Generic.List`1[[QuestBooks.QuestLog.QuestLineElement, QuestBooks]], System.Private.CoreLib",
          "$values": []
        },
        "NameKey": "Mods.QuestBooks.VanillaQuests.TestBook6.TestChapter1"
      },
      {
        "$type": "QuestBooks.QuestLog.DefaultQuestLines.BasicQuestLine, QuestBooks",
        "ChapterElements": {
          "$type": "System.Collections.Generic.List`1[[QuestBooks.QuestLog.QuestLineElement, QuestBooks]], System.Private.CoreLib",
          "$values": []
        },
        "NameKey": "Mods.QuestBooks.VanillaQuests.TestBook6.TestChapter2"
      },
      {
        "$type": "QuestBooks.QuestLog.DefaultQuestLines.BasicQuestLine, QuestBooks",
        "ChapterElements": {
          "$type": "System.Collections.Generic.List`1[[QuestBooks.QuestLog.QuestLineElement, QuestBooks]], System.Private.CoreLib",
          "$values": []
        },
        "NameKey": "Mods.QuestBooks.VanillaQuests.TestBook6.TestChapter3"
      },
      {
        "$type": "QuestBooks.QuestLog.DefaultQuestLines.BasicQuestLine, QuestBooks",
        "ChapterElements": {
          "$type": "System.Collections.Generic.List`1[[QuestBooks.QuestLog.QuestLineElement, QuestBooks]], System.Private.CoreLib",
          "$values": []
        },
        "NameKey": "Mods.QuestBooks.VanillaQuests.TestBook6.TestChapter4"
      },
      {
        "$type": "QuestBooks.QuestLog.DefaultQuestLines.BasicQuestLine, QuestBooks",
        "ChapterElements": {
          "$type": "System.Collections.Generic.List`1[[QuestBooks.QuestLog.QuestLineElement, QuestBooks]], System.Private.CoreLib",
          "$values": []
        },
        "NameKey": "Mods.QuestBooks.VanillaQuests.TestBook6.TestChapter5"
      }
    ]
  }
}